dataprocessor_client/__init__.py
dataprocessor_client/client.py
dataprocessor_client-0.0.2.dist-info/COPYING
dataprocessor_client-0.0.2.dist-info/METADATA
dataprocessor_client-0.0.2.dist-info/WHEEL
dataprocessor_client-0.0.2.dist-info/top_level.txt
dataprocessor_client-0.0.2.dist-info/RECORD
