Metadata-Version: 2.1
Name: dataprocessor-client
Version: 0.0.2
Summary: InterSCity DataProcessor client
Home-page: http://github.com/DylanGuedes/dataprocessor_client
Author: Dylan Guedes
Author-email: djmgguedes@gmail.com
License: MIT
Platform: UNKNOWN
